{
  "nodes": [
    {
      "id": "1",
      "type": "input",
      "dimensions": {
        "width": 150,
        "height": 36
      },
      "computedPosition": {
        "x": 100,
        "y": 100,
        "z": 0
      },
      "handleBounds": {
        "source": [
          {
            "id": null,
            "type": "source",
            "nodeId": "1",
            "position": "bottom",
            "x": 71,
            "y": 31,
            "width": 8,
            "height": 8
          }
        ],
        "target": null
      },
      "selected": false,
      "dragging": false,
      "resizing": false,
      "initialized": false,
      "isParent": false,
      "position": {
        "x": 100,
        "y": 100
      },
      "data": {
        "label": "Input Node"
      },
      "events": {}
    },
    {
      "id": "2",
      "type": "default",
      "dimensions": {
        "width": 150,
        "height": 36
      },
      "computedPosition": {
        "x": 300,
        "y": 100,
        "z": 0
      },
      "handleBounds": {
        "source": [
          {
            "id": null,
            "type": "source",
            "nodeId": "2",
            "position": "bottom",
            "x": 71,
            "y": 31,
            "width": 8,
            "height": 8
          }
        ],
        "target": [
          {
            "id": null,
            "type": "target",
            "nodeId": "2",
            "position": "top",
            "x": 71,
            "y": -3,
            "width": 8,
            "height": 8
          }
        ]
      },
      "selected": false,
      "dragging": false,
      "resizing": false,
      "initialized": false,
      "isParent": false,
      "position": {
        "x": 300,
        "y": 100
      },
      "data": {
        "label": "Output Node"
      },
      "events": {}
    },
    {
      "id": "6de7f2cb-842e-46d5-b280-02dbbdc05830",
      "type": "multi",
      "dimensions": {
        "width": 242,
        "height": 122
      },
      "computedPosition": {
        "x": 184.796875,
        "y": 276,
        "z": 0
      },
      "handleBounds": {
        "source": null,
        "target": null
      },
      "selected": false,
      "dragging": false,
      "resizing": false,
      "initialized": false,
      "isParent": false,
      "position": {
        "x": 184.796875,
        "y": 276
      },
      "data": {
        "nodeId": "6de7f2cb-842e-46d5-b280-02dbbdc05830",
        "label": "Composite action",
        "usedActionId": "54e50bf0-1c4a-40e6-ba37-19dc3b9d0de6",
        "ports": []
      },
      "events": {}
    }
  ],
  "edges": []
}